datasetops/__init__.py
datasetops/abstract.py
datasetops/compose.py
datasetops/dataset.py
datasetops/examples.py
datasetops/loaders.py
datasetops/types.py
datasetops-0.0.6.dist-info/LICENSE
datasetops-0.0.6.dist-info/METADATA
datasetops-0.0.6.dist-info/WHEEL
datasetops-0.0.6.dist-info/top_level.txt
datasetops-0.0.6.dist-info/RECORD
