Metadata-Version: 2.1
Name: datasetops
Version: 0.0.6
Summary: Fluent dataset operations, compatible with your favorite libraries
Home-page: https://github.com/LukasHedegaard/datasetops
Author: Lukas Hedegaard
License: UNKNOWN
Platform: UNKNOWN
Classifier: Programming Language :: Python :: 3
Classifier: License :: OSI Approved :: MIT License
Classifier: Operating System :: OS Independent
Classifier: Development Status :: 3 - Alpha
Classifier: Framework :: Pytest
Classifier: Topic :: Scientific/Engineering :: Artificial Intelligence
Requires-Python: >=3.6
Requires-Dist: numpy
Requires-Dist: pillow
Requires-Dist: pandas
Requires-Dist: scipy
Provides-Extra: build
Requires-Dist: setuptools ; extra == 'build'
Requires-Dist: wheel ; extra == 'build'
Requires-Dist: twine ; extra == 'build'
Provides-Extra: docs
Requires-Dist: Sphinx ; extra == 'docs'
Requires-Dist: recommonmark ; extra == 'docs'
Requires-Dist: sphinx-rtd-theme ; extra == 'docs'
Requires-Dist: sphinx-autoapi ; extra == 'docs'
Provides-Extra: tests
Requires-Dist: pytest ; extra == 'tests'
Requires-Dist: pytest-cov ; extra == 'tests'
Requires-Dist: flake8 ; extra == 'tests'
Requires-Dist: tensorflow ; extra == 'tests'
Requires-Dist: torch ; extra == 'tests'
Requires-Dist: torchvision ; extra == 'tests'
